{
	"title": "Spring Design",
	"intro": "Springs are crucial mechanical components in various industries, storing and releasing energy, absorbing shock, and maintaining force. They are designed to operate under cyclic loading while maintaining strength, elasticity, and fatigue resistance.",
	"technologies": ["CATIA V5"],
	"sections": [
		{
			"id": 1,
			"title": "Overview",
			"images": [
				{ "id": 1, "src": "/src/assets/PORTFOLIO-CAD-FEA/PORTFOLIO-11/SP-01.png" },
				{ "id": 2, "src": "/src/assets/PORTFOLIO-CAD-FEA/PORTFOLIO-11/SP-02.png" }
			]
		},
		{
			"id": 2,
			"title": "Draft",
			"content": "The draft of the design was created in Onshape. All dimensions are in millimeters.",
			"images": [{ "id": 3, "src": "/src/assets/PORTFOLIO-CAD-FEA/PORTFOLIO-11/SP-05.png" }]
		}
	]
}
